cards/__init__.py
cards/groups.yaml
cards/references.yaml
cards/rulings.yaml
cards/vtescrypt.csv
cards/vteslib.csv
cards/vteslibmeta.csv
cards/vtessets.csv
krcg/__init__.py
krcg/analyzer.py
krcg/cards.py
krcg/config.py
krcg/deck.py
krcg/parser.py
krcg/py.typed
krcg/rulings.py
krcg/seating.py
krcg/sets.py
krcg/twda.py
krcg/utils.py
krcg/vtes.py
krcg-4.15.dist-info/METADATA
krcg-4.15.dist-info/WHEEL
krcg-4.15.dist-info/licenses/LICENSE
krcg-4.15.dist-info/RECORD
