Metadata-Version: 2.4
Name: krcg
Version: 4.15
Summary: Library for VTES cards and TWDA.
Project-URL: Repository, https://github.com/lionel-panhaleux/krcg
Author-email: Lionel Panhaleux <lionel.panhaleux+krcg@gmail.com>
License-Expression: MIT
License-File: LICENSE
Keywords: CCG,TWD,TWDA,Vampire: The Eternal Struggle,vtes
Classifier: Development Status :: 5 - Production/Stable
Classifier: Intended Audience :: Developers
Classifier: Natural Language :: English
Classifier: Operating System :: OS Independent
Classifier: Programming Language :: Python :: 3
Classifier: Programming Language :: Python :: 3.10
Classifier: Programming Language :: Python :: 3.11
Classifier: Programming Language :: Python :: 3.12
Classifier: Programming Language :: Python :: 3.13
Classifier: Topic :: Software Development :: Libraries :: Python Modules
Requires-Python: >=3.10
Requires-Dist: arrow
Requires-Dist: numpy
Requires-Dist: pyyaml
Requires-Dist: requests
Requires-Dist: setuptools
Requires-Dist: unidecode
